pygame_core/__init__.py
pygame_core/animated_sprite.py
pygame_core/asset_manager.py
pygame_core/entity.py
pygame_core/game.py
pygame_core/game_context.py
pygame_core/input_manager.py
pygame_core/scene.py
pygame_core/scene_manager.py
pygame_core/settings.py
pygame_core/utils.py
pygame_core/dataclasses/__init__.py
pygame_core/dataclasses/size.py
pygame_core/dataclasses/sprite_sheet.py
pygame_pygame_core-0.1.33.dist-info/METADATA
pygame_pygame_core-0.1.33.dist-info/WHEEL
pygame_pygame_core-0.1.33.dist-info/top_level.txt
pygame_pygame_core-0.1.33.dist-info/RECORD
